nmeaparsec/__init__.py
nmeaparsec/nmea_parser.py
nmeaparsec-0.1.0.dist-info/licenses/LICENSE
nmeaparsec-0.1.0.dist-info/METADATA
nmeaparsec-0.1.0.dist-info/WHEEL
nmeaparsec-0.1.0.dist-info/top_level.txt
nmeaparsec-0.1.0.dist-info/RECORD
