Metadata-Version: 2.4
Name: nmeaparsec
Version: 0.1.0
Summary: A Python package for parsing NMEA data from GPS devices
Home-page: https://github.com/YavuzMuratt/nmeaparsec
Author: Yavuz Murat
Author-email: yyavuzmurat@gmail.com
Project-URL: Bug Reports, https://github.com/YavuzMuratt/nmeaparsec/issues
Project-URL: Source, https://github.com/YavuzMuratt/nmeaparsec
Classifier: Development Status :: 3 - Alpha
Classifier: Intended Audience :: Developers
Classifier: Intended Audience :: Science/Research
Classifier: License :: OSI Approved :: MIT License
Classifier: Operating System :: OS Independent
Classifier: Programming Language :: Python :: 3
Classifier: Programming Language :: Python :: 3.7
Classifier: Programming Language :: Python :: 3.8
Classifier: Programming Language :: Python :: 3.9
Classifier: Programming Language :: Python :: 3.10
Classifier: Topic :: Scientific/Engineering :: GIS
Classifier: Topic :: Software Development :: Libraries :: Python Modules
Classifier: Typing :: Typed
Requires-Python: >=3.7
License-File: LICENSE
Requires-Dist: numpy>=1.19.0
Provides-Extra: visualization
Requires-Dist: matplotlib>=3.3.0; extra == "visualization"
Dynamic: author
Dynamic: author-email
Dynamic: classifier
Dynamic: description
Dynamic: description-content-type
Dynamic: home-page
Dynamic: license-file
Dynamic: project-url
Dynamic: provides-extra
Dynamic: requires-dist
Dynamic: requires-python
Dynamic: summary
